diagraph/__init__.py
diagraph/assets/dist/diagraph-visualizer.js
diagraph/assets/dist/diagraph-visualizer.umd.cjs
diagraph/assets/dist/style.css
diagraph/classes/__init__.py
diagraph/classes/diagraph.py
diagraph/classes/diagraph_node.py
diagraph/classes/diagraph_node_group.py
diagraph/classes/diagraph_node_group_test.py
diagraph/classes/diagraph_node_test.py
diagraph/classes/diagraph_test.py
diagraph/classes/graph.py
diagraph/classes/graph_executor.py
diagraph/classes/graph_test.py
diagraph/classes/ordered_set.py
diagraph/classes/ordered_set_test.py
diagraph/classes/types.py
diagraph/classes/diagraph_state/__init__.py
diagraph/classes/diagraph_state/binary_search.py
diagraph/classes/diagraph_state/binary_search_test.py
diagraph/classes/diagraph_state/diagraph_state.py
diagraph/classes/diagraph_state/diagraph_state_record.py
diagraph/classes/diagraph_state/diagraph_state_record_test.py
diagraph/classes/diagraph_state/diagraph_state_test.py
diagraph/classes/diagraph_state/types.py
diagraph/classes/serializers/__init__.py
diagraph/classes/serializers/get_fn.py
diagraph/classes/serializers/get_fn_test.py
diagraph/classes/serializers/v1.py
diagraph/classes/serializers/v1_test.py
diagraph/decorators/__init__.py
diagraph/decorators/is_decorated.py
diagraph/decorators/prompt.py
diagraph/decorators/prompt_test.py
diagraph/llm/__init__.py
diagraph/llm/llm.py
diagraph/llm/openai_llm/__init__.py
diagraph/llm/openai_llm/build_dict.py
diagraph/llm/openai_llm/build_dict_test.py
diagraph/llm/openai_llm/cast_to_input.py
diagraph/llm/openai_llm/cast_to_input_test.py
diagraph/llm/openai_llm/openai_llm.py
diagraph/llm/openai_llm/openai_llm_test.py
diagraph/utils/__init__.py
diagraph/utils/build_graph.py
diagraph/utils/build_graph_test.py
diagraph/utils/build_parameters.py
diagraph/utils/build_parameters_test.py
diagraph/utils/depends.py
diagraph/utils/depends_test.py
diagraph/utils/get_execution_graph.py
diagraph/utils/get_execution_graph_test.py
diagraph/utils/get_filetype.py
diagraph-0.4.7.dist-info/LICENSE
diagraph-0.4.7.dist-info/METADATA
diagraph-0.4.7.dist-info/WHEEL
diagraph-0.4.7.dist-info/top_level.txt
diagraph-0.4.7.dist-info/RECORD
