Metadata-Version: 2.1
Name: diagraph
Version: 0.4.7
Summary: DAGs for LLM interactions
Author-email: Ambient Labs <maintainers@diagraph.dev>
Project-URL: Homepage, https://github.com/ambient-labs/diagraph
Project-URL: Bug Tracker, https://github.com/ambient-labs/diagraph/issues
Classifier: Programming Language :: Python :: 3
Classifier: License :: OSI Approved :: MIT License
Classifier: Operating System :: OS Independent
Requires-Python: >=3.10
License-File: LICENSE
Requires-Dist: pydantic
Requires-Dist: networkx
Requires-Dist: openai >=1.3.0
Requires-Dist: tiktoken
